{"chunk_definitions":[{"row":11,"row_count":1,"visible":true,"expansion_state":0,"options":{"engine":"r","label":"unnamed-chunk-23"},"document_id":"0946AC29","chunk_id":"cgmyy734xj2g6","chunk_label":"unnamed-chunk-1"},{"row":25,"row_count":1,"visible":true,"expansion_state":0,"options":{"engine":"r","label":"unnamed-chunk-24"},"document_id":"0946AC29","chunk_id":"cysprslr3bdfn","chunk_label":"unnamed-chunk-2"},{"row":36,"row_count":1,"visible":true,"expansion_state":0,"options":{"engine":"r","label":"unnamed-chunk-25"},"document_id":"0946AC29","chunk_id":"ckhq1tv6u4z6b","chunk_label":"unnamed-chunk-3"},{"row":43,"row_count":1,"visible":true,"expansion_state":0,"options":{"engine":"r","label":"unnamed-chunk-26"},"document_id":"0946AC29","chunk_id":"c4q4t1py6u2ap","chunk_label":"unnamed-chunk-4"},{"row":51,"row_count":1,"visible":true,"expansion_state":0,"options":{"engine":"r","label":"unnamed-chunk-27"},"document_id":"0946AC29","chunk_id":"cdqx6akuofqu5","chunk_label":"unnamed-chunk-5"},{"row":58,"row_count":1,"visible":true,"expansion_state":0,"options":{"engine":"r","label":"unnamed-chunk-28"},"document_id":"0946AC29","chunk_id":"c8p2lcfdgiw1u","chunk_label":"unnamed-chunk-6"},{"row":66,"row_count":1,"visible":true,"expansion_state":0,"options":{"engine":"r","label":"unnamed-chunk-29"},"document_id":"0946AC29","chunk_id":"cglimxzgzgame","chunk_label":"unnamed-chunk-7"},{"row":74,"row_count":1,"visible":true,"expansion_state":0,"options":{"engine":"r","label":"unnamed-chunk-30"},"document_id":"0946AC29","chunk_id":"cpbhym9tbkxy1","chunk_label":"unnamed-chunk-8"},{"row":81,"row_count":1,"visible":true,"expansion_state":0,"options":{"engine":"r","label":"unnamed-chunk-31"},"document_id":"0946AC29","chunk_id":"c4oyd6r8dp6xy","chunk_label":"unnamed-chunk-9"},{"row":96,"row_count":1,"visible":true,"expansion_state":0,"options":{"engine":"r","label":"unnamed-chunk-32"},"document_id":"0946AC29","chunk_id":"cp4tnxxw2x3wf","chunk_label":"unnamed-chunk-10"},{"row":123,"row_count":1,"visible":true,"expansion_state":0,"options":{"engine":"r","label":"unnamed-chunk-37"},"document_id":"0946AC29","chunk_id":"cj2y0hpc35mar","chunk_label":"unnamed-chunk-11"},{"row":131,"row_count":1,"visible":true,"expansion_state":0,"options":{"engine":"r","label":"unnamed-chunk-36"},"document_id":"0946AC29","chunk_id":"cdxwnuk6loenc","chunk_label":"unnamed-chunk-12"},{"row":137,"row_count":1,"visible":true,"expansion_state":0,"options":{"engine":"r","label":"unnamed-chunk-40"},"document_id":"0946AC29","chunk_id":"cgjv6nqtwgufo","chunk_label":"unnamed-chunk-13"},{"row":157,"row_count":1,"visible":true,"expansion_state":0,"options":{"engine":"r","label":"unnamed-chunk-50"},"document_id":"0946AC29","chunk_id":"cyyc0sp5x3t6z","chunk_label":"unnamed-chunk-14"}],"doc_write_time":1660685502}